departing/__init__.py
departing/model.py
departing-0.0.2.dist-info/LICENSE
departing-0.0.2.dist-info/METADATA
departing-0.0.2.dist-info/WHEEL
departing-0.0.2.dist-info/entry_points.txt
departing-0.0.2.dist-info/top_level.txt
departing-0.0.2.dist-info/RECORD
