Metadata-Version: 2.1
Name: departing
Version: 0.0.2
Summary: Interface for departing.ai
Home-page: https://github.com/pappacena/project_urlname/
Author: pappacena
License-File: LICENSE
Requires-Dist: requests
Provides-Extra: test
Requires-Dist: pytest ; extra == 'test'
Requires-Dist: coverage ; extra == 'test'
Requires-Dist: flake8 ; extra == 'test'
Requires-Dist: black ; extra == 'test'
Requires-Dist: isort ; extra == 'test'
Requires-Dist: pytest-cov ; extra == 'test'
Requires-Dist: codecov ; extra == 'test'
Requires-Dist: mypy ; extra == 'test'
Requires-Dist: gitchangelog ; extra == 'test'
Requires-Dist: mkdocs ; extra == 'test'
Requires-Dist: types-requests ; extra == 'test'
Requires-Dist: ipdb ; extra == 'test'
